License.txt
README.md
setup.py
development_tool.egg-info/PKG-INFO
development_tool.egg-info/SOURCES.txt
development_tool.egg-info/dependency_links.txt
development_tool.egg-info/entry_points.txt
development_tool.egg-info/namespace_packages.txt
development_tool.egg-info/requires.txt
development_tool.egg-info/top_level.txt
orangecontrib/__init__.py
orangecontrib/development_tool/__init__.py
orangecontrib/development_tool/widgets/__init__.py
orangecontrib/development_tool/widgets/table_editor.py
orangecontrib/development_tool/widgets/dataset_devellopper/fake_input.csv
orangecontrib/development_tool/widgets/dataset_devellopper/fakeows.ows
orangecontrib/development_tool/widgets/dataset_devellopper/readme.txt
orangecontrib/development_tool/widgets/icons/Emblem_of_Napoleon_Bonaparte.svg
orangecontrib/development_tool/widgets/icons/Logo_HKH.svg
orangecontrib/development_tool/widgets/icons/Logo_HKH_4.svg
orangecontrib/development_tool/widgets/icons/Logo_HKH_4_jc.svg
orangecontrib/development_tool/widgets/icons/Napoleon2.svg
orangecontrib/development_tool/widgets/icons/Pikachu SVG File.svg
orangecontrib/development_tool/widgets/icons/Workflow.svg
orangecontrib/development_tool/widgets/icons/category.svg
orangecontrib/development_tool/widgets/icons/chat-bot.png
orangecontrib/development_tool/widgets/icons/data-integration.png
orangecontrib/development_tool/widgets/icons/database.svg
orangecontrib/development_tool/widgets/icons/documents.png
orangecontrib/development_tool/widgets/icons/download-svgrepo-com.svg
orangecontrib/development_tool/widgets/icons/duplicate.png
orangecontrib/development_tool/widgets/icons/ecriture.svg
orangecontrib/development_tool/widgets/icons/file-transfer.png
orangecontrib/development_tool/widgets/icons/goto.png
orangecontrib/development_tool/widgets/icons/icon_surrogate_learner.png
orangecontrib/development_tool/widgets/icons/icon_surrogate_predict.png
orangecontrib/development_tool/widgets/icons/input.png
orangecontrib/development_tool/widgets/icons/interrupteur.svg
orangecontrib/development_tool/widgets/icons/jcm_export_score.png
orangecontrib/development_tool/widgets/icons/jcm_open_file_resize_alpha_channel.png
orangecontrib/development_tool/widgets/icons/jcm_optuna_parameters_setting.png
