Metadata-Version: 1.0
Name: development-tool
Version: 0.6.66
Summary: Library of developed widgets
Home-page: UNKNOWN
Author: alex_hkh
Author-email: UNKNOWN
License: UNKNOWN
Keywords: orange3 add-on
Platform: UNKNOWN
